tqdx/__init__.py
tqdx/callbacks.py
tqdx/rich/__init__.py
tqdx/rich/callbacks.py
tqdx/rich/wrappers.py
tqdx/wrappers.py
tqdx-0.1.5.dist-info/METADATA
tqdx-0.1.5.dist-info/WHEEL
tqdx-0.1.5.dist-info/licenses/LICENSE
tqdx-0.1.5.dist-info/RECORD
