Metadata-Version: 2.4
Name: tqdx
Version: 0.1.5
Summary: JAX compatible progress bars for scan and fori_loop.
License-Expression: MIT
License-File: LICENSE
Author: huterguier
Author-email: huterguier@gmail.com
Requires-Python: >=3.9
Classifier: Programming Language :: Python :: 3
Classifier: Operating System :: OS Independent
Provides-Extra: dev
Requires-Dist: black ; extra == "dev"
Requires-Dist: isort ; extra == "dev"
Requires-Dist: jax (>=0.4.25)
Requires-Dist: rich (>=14.0.0)
Requires-Dist: tqdm (>=4.66.1)
Project-URL: Homepage, https://github.com/huterguier/tqdx
